netpalm_client/__init__.py
netpalm_client/netpalm_client.py
netpalm_client/utils.py
netpalm_client-1.0.4.dist-info/LICENSE
netpalm_client-1.0.4.dist-info/WHEEL
netpalm_client-1.0.4.dist-info/METADATA
netpalm_client-1.0.4.dist-info/RECORD
