Metadata-Version: 2.1
Name: netpalm-client
Version: 1.0.4
Summary: Simple Client for accessing a Netpalm Service
License: MIT
Author: Will George
Author-email: wrgeorge1983@gmail.com
Requires-Python: >=3.7,<4.0
Classifier: License :: OSI Approved :: MIT License
Classifier: Programming Language :: Python :: 3
Classifier: Programming Language :: Python :: 3.7
Classifier: Programming Language :: Python :: 3.8
Classifier: Programming Language :: Python :: 3.9
Requires-Dist: requests (>=2.25.1,<3.0.0)
